[
  {
    "file": "abd-al-qadir-al-jazairi.json",
    "name": "Abd al-Qadir al-Jazairi"
  },
  {
    "file": "abd-al-qadir-jilani.json",
    "name": "Abd al-Qadir al-Jilani"
  },
  {
    "file": "abdul-qadir-al-jilani.json",
    "name": "Abdul Qadir al-Jilani"
  },
  {
    "file": "abu-bakr.json",
    "name": "Abu Bakr as-Siddiq"
  },
  {
    "file": "abu-dawud.json",
    "name": "Abu Dawud al-Sijistani"
  },
  {
    "file": "abu-dulaf.json",
    "name": "Abu Dulaf al-Khazraji"
  },
  {
    "file": "abu-hanifa.json",
    "name": "Abu Hanifa"
  },
  {
    "file": "ahmad-baba-al-timbukti.json",
    "name": "Ahmad Baba al-Timbukti"
  },
  {
    "file": "ahmad-ibn-hanbal.json",
    "name": "Imam Ahmad ibn Hanbal"
  },
  {
    "file": "ahmad-ibn-majid.json",
    "name": "Ahmad ibn Majid"
  },
  {
    "file": "ahmad-sirhindi.json",
    "name": "Ahmad Sirhindi"
  },
  {
    "file": "ahmadu-bamba.json",
    "name": "Ahmadu Bamba"
  },
  {
    "file": "aisha-bint-abi-bakr.json",
    "name": "Aisha bint Abi Bakr"
  },
  {
    "file": "akbar.json",
    "name": "Akbar the Great"
  },
  {
    "file": "al-battani.json",
    "name": "Al-Battani"
  },
  {
    "file": "al-biruni.json",
    "name": "Al-Biruni"
  },
  {
    "file": "al-bukhari.json",
    "name": "Imam al-Bukhari"
  },
  {
    "file": "al-dhahabi.json",
    "name": "Al-Dhahabi"
  },
  {
    "file": "al-farabi.json",
    "name": "Al-Farabi"
  },
  {
    "file": "al-ghazali.json",
    "name": "Al-Ghazali"
  },
  {
    "file": "al-hallaj.json",
    "name": "Al-Hallaj"
  },
  {
    "file": "al-idrisi.json",
    "name": "Al-Idrisi"
  },
  {
    "file": "al-istakhri.json",
    "name": "Al-Istakhri"
  },
  {
    "file": "al-khatib-al-baghdadi.json",
    "name": "Al-Khatib al-Baghdadi"
  },
  {
    "file": "al-khwarizmi.json",
    "name": "Al-Khwarizmi"
  },
  {
    "file": "al-kindi.json",
    "name": "Al-Kindi"
  },
  {
    "file": "al-mamun.json",
    "name": "Al-Ma'mun"
  },
  {
    "file": "al-maqrizi.json",
    "name": "Al-Maqrizi"
  },
  {
    "file": "al-masudi.json",
    "name": "Al-Masudi"
  },
  {
    "file": "al-muqaddasi.json",
    "name": "Al-Muqaddasi (Shams al-Din al-Maqdisi)"
  },
  {
    "file": "al-qazwini.json",
    "name": "Al-Qazwini"
  },
  {
    "file": "al-razi.json",
    "name": "Al-Razi (Rhazes)"
  },
  {
    "file": "al-sakhawi.json",
    "name": "Al-Sakhawi"
  },
  {
    "file": "al-shadhili.json",
    "name": "Abu al-Hasan al-Shadhili"
  },
  {
    "file": "al-shafii.json",
    "name": "Imam al-Shafi'i"
  },
  {
    "file": "al-shatibi.json",
    "name": "Al-Shatibi"
  },
  {
    "file": "al-shawkani.json",
    "name": "Al-Shawkani"
  },
  {
    "file": "al-suyuti.json",
    "name": "Jalal al-Din al-Suyuti"
  },
  {
    "file": "al-tabari.json",
    "name": "Al-Tabari"
  },
  {
    "file": "al-tirmidhi.json",
    "name": "Al-Tirmidhi"
  },
  {
    "file": "al-yaqubi.json",
    "name": "Al-Ya'qubi"
  },
  {
    "file": "al-zahrawi.json",
    "name": "Al-Zahrawi (Abulcasis)"
  },
  {
    "file": "ali-al-hujwiri.json",
    "name": "Ali al-Hujwiri (Data Ganj Bakhsh)"
  },
  {
    "file": "ali-al-ridha.json",
    "name": "Ali al-Ridha"
  },
  {
    "file": "ali-ibn-abi-talib.json",
    "name": "Ali ibn Abi Talib"
  },
  {
    "file": "alp-arslan.json",
    "name": "Alp Arslan"
  },
  {
    "file": "amir-khusrau.json",
    "name": "Amir Khusrau"
  },
  {
    "file": "amr-ibn-al-as.json",
    "name": "Amr ibn al-As"
  },
  {
    "file": "attar-of-nishapur.json",
    "name": "Farid al-Din Attar"
  },
  {
    "file": "attar.json",
    "name": "Farid ud-Din Attar"
  },
  {
    "file": "aurangzeb.json",
    "name": "Aurangzeb"
  },
  {
    "file": "babur.json",
    "name": "Babur"
  },
  {
    "file": "baha-al-din-naqshband.json",
    "name": "Baha al-Din Naqshband"
  },
  {
    "file": "bahauddin-naqshband.json",
    "name": "Baha-ud-Din Naqshband"
  },
  {
    "file": "bayazid-bistami.json",
    "name": "Bayazid Bistami"
  },
  {
    "file": "baybars.json",
    "name": "Baybars"
  },
  {
    "file": "bulleh-shah.json",
    "name": "Bulleh Shah"
  },
  {
    "file": "dara-shikoh.json",
    "name": "Dara Shikoh"
  },
  {
    "file": "dhul-nun-al-misri.json",
    "name": "Dhul-Nun al-Misri"
  },
  {
    "file": "evliya-celebi.json",
    "name": "Evliya Çelebi"
  },
  {
    "file": "fakhr-al-din-al-razi.json",
    "name": "Fakhr al-Din al-Razi"
  },
  {
    "file": "fatimah-al-zahra.json",
    "name": "Fatimah al-Zahra"
  },
  {
    "file": "hafez.json",
    "name": "Hafez of Shiraz"
  },
  {
    "file": "haji-bektash-veli.json",
    "name": "Haji Bektash Veli"
  },
  {
    "file": "harun-al-rashid.json",
    "name": "Harun al-Rashid"
  },
  {
    "file": "hasan-al-basri.json",
    "name": "Hasan al-Basri"
  },
  {
    "file": "hasan-ibn-ali.json",
    "name": "Hasan ibn Ali"
  },
  {
    "file": "hayreddin-barbarossa.json",
    "name": "Hayreddin Barbarossa"
  },
  {
    "file": "humayun.json",
    "name": "Humayun"
  },
  {
    "file": "husayn-ibn-ali.json",
    "name": "Husayn ibn Ali"
  },
  {
    "file": "ibn-al-arabi.json",
    "name": "Ibn al-Arabi"
  },
  {
    "file": "ibn-al-haytham.json",
    "name": "Ibn al-Haytham"
  },
  {
    "file": "ibn-al-jawzi.json",
    "name": "Ibn al-Jawzi"
  },
  {
    "file": "ibn-al-nafis.json",
    "name": "Ibn al-Nafis"
  },
  {
    "file": "ibn-arabi.json",
    "name": "Ibn Arabi"
  },
  {
    "file": "ibn-asakir.json",
    "name": "Ibn Asakir"
  },
  {
    "file": "ibn-battuta.json",
    "name": "Ibn Battuta"
  },
  {
    "file": "ibn-fadlan.json",
    "name": "Ibn Fadlan"
  },
  {
    "file": "ibn-hajar-al-asqalani.json",
    "name": "Ibn Hajar al-Asqalani"
  },
  {
    "file": "ibn-hawqal.json",
    "name": "Ibn Hawqal"
  },
  {
    "file": "ibn-hazm.json",
    "name": "Ibn Hazm"
  },
  {
    "file": "ibn-jubayr.json",
    "name": "Ibn Jubayr"
  },
  {
    "file": "ibn-khaldun.json",
    "name": "Ibn Khaldun"
  },
  {
    "file": "ibn-rushd.json",
    "name": "Ibn Rushd"
  },
  {
    "file": "ibn-rustah.json",
    "name": "Ibn Rustah"
  },
  {
    "file": "ibn-sina.json",
    "name": "Ibn Sina"
  },
  {
    "file": "ibn-taymiyya.json",
    "name": "Ibn Taymiyya"
  },
  {
    "file": "ibn-tufayl.json",
    "name": "Ibn Tufayl"
  },
  {
    "file": "ibrahim-ibn-adham.json",
    "name": "Ibrahim ibn Adham"
  },
  {
    "file": "imam-malik.json",
    "name": "Imam Malik ibn Anas"
  },
  {
    "file": "imam-muslim.json",
    "name": "Imam Muslim"
  },
  {
    "file": "iqbal.json",
    "name": "Allama Iqbal"
  },
  {
    "file": "jabir-ibn-hayyan.json",
    "name": "Jabir ibn Hayyan"
  },
  {
    "file": "jafar-al-sadiq.json",
    "name": "Ja'far al-Sadiq"
  },
  {
    "file": "jahangir.json",
    "name": "Jahangir"
  },
  {
    "file": "jamal-al-din-al-afghani.json",
    "name": "Jamal al-Din al-Afghani"
  },
  {
    "file": "jami.json",
    "name": "Abd al-Rahman Jami"
  },
  {
    "file": "junayd-al-baghdadi.json",
    "name": "Junayd al-Baghdadi"
  },
  {
    "file": "khadija-bint-khuwaylid.json",
    "name": "Khadija bint Khuwaylid"
  },
  {
    "file": "khalid-ibn-al-walid.json",
    "name": "Khalid ibn al-Walid"
  },
  {
    "file": "leo-africanus.json",
    "name": "Leo Africanus"
  },
  {
    "file": "mansa-musa.json",
    "name": "Mansa Musa"
  },
  {
    "file": "mehmed-ii.json",
    "name": "Mehmed II the Conqueror"
  },
  {
    "file": "mimar-sinan.json",
    "name": "Mimar Sinan"
  },
  {
    "file": "moinuddin-chishti.json",
    "name": "Moinuddin Chishti"
  },
  {
    "file": "muawiya.json",
    "name": "Muawiya ibn Abi Sufyan"
  },
  {
    "file": "muhammad-abduh.json",
    "name": "Muhammad Abduh"
  },
  {
    "file": "muhammad-al-baqir.json",
    "name": "Muhammad al-Baqir"
  },
  {
    "file": "mulla-sadra.json",
    "name": "Mulla Sadra"
  },
  {
    "file": "muslim-ibn-al-hajjaj.json",
    "name": "Muslim ibn al-Hajjaj"
  },
  {
    "file": "nana-asmau.json",
    "name": "Nana Asma'u"
  },
  {
    "file": "nasir-al-din-al-tusi.json",
    "name": "Nasir al-Din al-Tusi"
  },
  {
    "file": "nasir-khusraw.json",
    "name": "Nasir Khusraw"
  },
  {
    "file": "nizami-ganjavi.json",
    "name": "Nizami Ganjavi"
  },
  {
    "file": "nizamuddin-auliya.json",
    "name": "Nizamuddin Auliya"
  },
  {
    "file": "nizamuddin-awliya.json",
    "name": "Nizamuddin Awliya"
  },
  {
    "file": "nur-al-din-zangi.json",
    "name": "Nur al-Din Zangi"
  },
  {
    "file": "omar-khayyam.json",
    "name": "Omar Khayyam"
  },
  {
    "file": "piri-reis.json",
    "name": "Piri Reis"
  },
  {
    "file": "prophet-muhammad.json",
    "name": "Prophet Muhammad"
  },
  {
    "file": "qaitbay.json",
    "name": "Qaitbay"
  },
  {
    "file": "qalawun.json",
    "name": "Qalawun"
  },
  {
    "file": "rabia-al-adawiyya.json",
    "name": "Rabia al-Adawiyya"
  },
  {
    "file": "rabia-al-basri.json",
    "name": "Rabia al-Basri"
  },
  {
    "file": "rumi.json",
    "name": "Jalal ad-Din Rumi"
  },
  {
    "file": "saadi-shirazi.json",
    "name": "Saadi Shirazi"
  },
  {
    "file": "said-nursi.json",
    "name": "Bediuzzaman Said Nursi"
  },
  {
    "file": "saladin.json",
    "name": "Salahuddin Ayyubi"
  },
  {
    "file": "selim-i.json",
    "name": "Selim I"
  },
  {
    "file": "seydi-ali-reis.json",
    "name": "Seydi Ali Reis"
  },
  {
    "file": "shah-abbas-i.json",
    "name": "Shah Abbas I"
  },
  {
    "file": "shah-ismail-i.json",
    "name": "Shah Isma'il I"
  },
  {
    "file": "shah-jahan.json",
    "name": "Shah Jahan"
  },
  {
    "file": "shah-waliullah.json",
    "name": "Shah Waliullah"
  },
  {
    "file": "shams-i-tabrizi.json",
    "name": "Shams-i Tabrizi"
  },
  {
    "file": "sulayman-al-mahri.json",
    "name": "Sulayman al-Mahri"
  },
  {
    "file": "suleiman-i.json",
    "name": "Suleiman the Magnificent"
  },
  {
    "file": "suleiman.json",
    "name": "Suleiman the Magnificent"
  },
  {
    "file": "tariq-ibn-ziyad.json",
    "name": "Tariq ibn Ziyad"
  },
  {
    "file": "timur.json",
    "name": "Timur (Tamerlane)"
  },
  {
    "file": "tipu-sultan.json",
    "name": "Tipu Sultan"
  },
  {
    "file": "ulugh-beg.json",
    "name": "Ulugh Beg"
  },
  {
    "file": "umar-ibn-abd-al-aziz.json",
    "name": "Umar ibn Abd al-Aziz"
  },
  {
    "file": "umar-ibn-al-khattab.json",
    "name": "Umar ibn al-Khattab"
  },
  {
    "file": "usman-dan-fodio.json",
    "name": "Usman dan Fodio"
  },
  {
    "file": "uthman-ibn-affan.json",
    "name": "Uthman ibn Affan"
  },
  {
    "file": "yaqut-al-hamawi.json",
    "name": "Yaqut al-Hamawi"
  },
  {
    "file": "yunus-emre.json",
    "name": "Yunus Emre"
  },
  {
    "file": "yusuf-ibn-tashfin.json",
    "name": "Yusuf ibn Tashfin"
  },
  {
    "file": "zayn-al-abidin.json",
    "name": "Ali ibn al-Husayn Zayn al-Abidin"
  },
  {
    "file": "zheng-he.json",
    "name": "Zheng He"
  }
]