{
  "person": "Prophet Muhammad",
  "slug": "F1132",
  "lifespan": { "birth": 570, "death": 632 },
  "schema_version": 1,
  "confidence": {
    "grade": "A",
    "density": "high",
    "precision": "high",
    "disclosure": "The Prophet's life is the most documented in early Islamic history, anchored in Ibn Ishaq's sirah and the hadith collections. The Medinan decade (622-632) is attested at month-level precision from multiple independent early sources. Childhood and pre-prophethood entries (marked 'year' or 'period') draw on later traditional reports and should be read as traditional rather than strictly documented. Sources were compiled 100-200 years after his death."
  },
  "sources": [
    "Ibn Ishaq, Sirat Rasul Allah",
    "Al-Tabari, Tarikh al-Rusul wa al-Muluk",
    "Sahih al-Bukhari",
    "Sahih Muslim",
    "Ibn Hisham, Al-Sirah al-Nabawiyyah",
    "Ibn Sa'd, Kitab al-Tabaqat al-Kabir"
  ],
  "journey": [
    {
      "year": 570,
      "age": 0,
      "precision": "year",
      "location": "Mecca",
      "lat": 21.4225,
      "lng": 39.8262,
      "event": "Born in the Year of the Elephant into the Banu Hashim clan of the Quraysh tribe. His father Abdullah had died before his birth.",
      "category": "birth",
      "source": "Ibn Ishaq; Ibn Sa'd"
    },
    {
      "year": 570,
      "age": 0,
      "precision": "period",
      "period_end": 575,
      "location": "Banu Sa'd (desert near Ta'if)",
      "lat": 21.27,
      "lng": 40.42,
      "event": "Sent to be nursed and raised in the desert by Halimah al-Sa'diyya, following the Quraysh custom of sending infants to Bedouin foster families for a healthier upbringing.",
      "category": "childhood",
      "source": "Ibn Ishaq; Ibn Sa'd"
    },
    {
      "year": 576,
      "age": 6,
      "precision": "year",
      "location": "Al-Abwa",
      "lat": 23.08,
      "lng": 39.19,
      "event": "His mother Aminah bint Wahb died on the return journey from visiting relatives in Medina. He was orphaned at the age of six.",
      "category": "loss",
      "source": "Ibn Ishaq; Ibn Hisham"
    },
    {
      "year": 578,
      "age": 8,
      "precision": "year",
      "location": "Mecca",
      "lat": 21.4225,
      "lng": 39.8262,
      "event": "His grandfather and guardian Abd al-Muttalib died. Care passed to his uncle Abu Talib, chief of Banu Hashim.",
      "category": "loss",
      "source": "Ibn Ishaq"
    },
    {
      "year": 583,
      "age": 12,
      "precision": "year",
      "location": "Bosra (Syria)",
      "lat": 32.52,
      "lng": 36.48,
      "event": "Travelled with his uncle Abu Talib on a trading caravan to Syria. The monk Bahira reportedly recognised signs of prophethood in the young boy.",
      "category": "travel",
      "source": "Ibn Ishaq; Al-Tirmidhi"
    },
    {
      "year": 595,
      "age": 25,
      "precision": "year",
      "location": "Mecca",
      "lat": 21.4225,
      "lng": 39.8262,
      "event": "Married Khadijah bint Khuwaylid, a successful merchant widow fifteen years his senior. She had employed him to lead her trading caravan to Syria and proposed marriage after being impressed by his character.",
      "category": "marriage",
      "source": "Ibn Ishaq; Sahih al-Bukhari"
    },
    {
      "year": 605,
      "age": 35,
      "precision": "year",
      "location": "Mecca (Ka'bah)",
      "lat": 21.4225,
      "lng": 39.8262,
      "event": "Arbitrated a dispute among Quraysh clans over who should place the Black Stone during the rebuilding of the Ka'bah. He placed it on a cloth and had representatives of each clan carry it together.",
      "category": "civic",
      "source": "Ibn Ishaq; Ibn Hisham"
    },
    {
      "year": 610,
      "month": 8,
      "age": 40,
      "precision": "month",
      "location": "Cave of Hira (Jabal al-Nour)",
      "lat": 21.4575,
      "lng": 39.8583,
      "event": "Received the first revelation from the Angel Jibril during a retreat in the Cave of Hira. The first verses revealed were the opening of Surah Al-Alaq: 'Read in the name of your Lord who created.'",
      "category": "revelation",
      "source": "Sahih al-Bukhari; Sahih Muslim"
    },
    {
      "year": 613,
      "age": 43,
      "precision": "year",
      "location": "Mecca (Mount Safa)",
      "lat": 21.4234,
      "lng": 39.8267,
      "event": "Began public preaching, calling the Quraysh from Mount Safa. Most of the tribal leaders rejected the message, but a small community of believers began to form.",
      "category": "preaching",
      "source": "Sahih al-Bukhari; Ibn Ishaq"
    },
    {
      "year": 615,
      "age": 45,
      "precision": "year",
      "location": "Mecca",
      "lat": 21.4225,
      "lng": 39.8262,
      "event": "Persecution of Muslims by the Quraysh intensified. He instructed a group of followers to emigrate to Abyssinia (Ethiopia) to seek protection under the just Christian king, the Negus.",
      "category": "persecution",
      "source": "Ibn Ishaq; Ibn Hisham"
    },
    {
      "year": 616,
      "age": 46,
      "precision": "period",
      "period_end": 619,
      "location": "Shi'b Abi Talib (Mecca)",
      "lat": 21.4280,
      "lng": 39.8230,
      "event": "The Quraysh imposed a total boycott on Banu Hashim and Banu al-Muttalib. The clans were confined to a narrow valley, cut off from trade and social contact for approximately three years.",
      "category": "persecution",
      "source": "Ibn Ishaq; Ibn Sa'd"
    },
    {
      "year": 619,
      "age": 49,
      "precision": "year",
      "location": "Mecca",
      "lat": 21.4225,
      "lng": 39.8262,
      "event": "The Year of Sorrow. His wife Khadijah and his uncle Abu Talib both died within weeks of each other, removing his closest emotional support and his clan's political protection.",
      "category": "loss",
      "source": "Ibn Ishaq; Ibn Sa'd"
    },
    {
      "year": 619,
      "age": 49,
      "precision": "year",
      "location": "Ta'if",
      "lat": 21.2703,
      "lng": 40.4158,
      "event": "Travelled to Ta'if to seek support from the Thaqif tribe. He was rejected and stoned by the townspeople. He prayed for their guidance rather than their destruction.",
      "category": "rejection",
      "source": "Ibn Ishaq; Ibn Hisham"
    },
    {
      "year": 621,
      "age": 51,
      "precision": "year",
      "location": "Mecca / Jerusalem",
      "lat": 31.7781,
      "lng": 35.2354,
      "event": "The Night Journey (Isra) and Ascension (Mi'raj). Transported from the Sacred Mosque in Mecca to Al-Aqsa in Jerusalem, then ascended through the heavens. The five daily prayers were prescribed during this journey.",
      "category": "spiritual",
      "source": "Sahih al-Bukhari; Sahih Muslim; Quran 17:1"
    },
    {
      "year": 621,
      "age": 51,
      "precision": "year",
      "location": "Mina (near Mecca)",
      "lat": 21.4133,
      "lng": 39.8933,
      "event": "The First Pledge of Aqaba. Twelve men from Yathrib (Medina) pledged allegiance, accepting Islam and promising to uphold its moral principles.",
      "category": "pledge",
      "source": "Ibn Ishaq; Ibn Hisham"
    },
    {
      "year": 622,
      "age": 52,
      "precision": "year",
      "location": "Mina (near Mecca)",
      "lat": 21.4133,
      "lng": 39.8933,
      "event": "The Second Pledge of Aqaba. Seventy-five people from Yathrib pledged to protect him as they would their own families, paving the way for the migration.",
      "category": "pledge",
      "source": "Ibn Ishaq; Sahih Muslim"
    },
    {
      "year": 622,
      "month": 9,
      "age": 52,
      "precision": "month",
      "location": "Cave of Thawr (south of Mecca)",
      "lat": 21.3767,
      "lng": 39.8486,
      "event": "Departed Mecca secretly with Abu Bakr. They hid in the Cave of Thawr for three days while Quraysh search parties scoured the area. A spider's web and a dove's nest at the cave entrance are reported to have concealed them.",
      "category": "migration",
      "source": "Sahih al-Bukhari; Quran 9:40"
    },
    {
      "year": 622,
      "month": 9,
      "age": 52,
      "precision": "month",
      "location": "Quba (outskirts of Medina)",
      "lat": 24.4392,
      "lng": 39.6172,
      "event": "Arrived at Quba after travelling north along the coastal route. Established the first mosque in Islam, Masjid Quba, during a stay of several days.",
      "category": "migration",
      "source": "Ibn Ishaq; Sahih al-Bukhari"
    },
    {
      "year": 622,
      "month": 9,
      "age": 52,
      "precision": "month",
      "location": "Medina",
      "lat": 24.4686,
      "lng": 39.6142,
      "event": "Entered Medina to a joyful reception. His camel knelt at the site where the Prophet's Mosque (Masjid al-Nabawi) would be built. Established the Constitution of Medina, a multi-faith social contract.",
      "category": "migration",
      "source": "Ibn Ishaq; Sahih al-Bukhari"
    },
    {
      "year": 624,
      "month": 3,
      "age": 53,
      "precision": "month",
      "location": "Wells of Badr",
      "lat": 23.7833,
      "lng": 38.7833,
      "event": "The Battle of Badr. A force of 313 Muslims defeated a Quraysh army of nearly 1,000. This decisive victory established the Muslim community as a political and military force in Arabia.",
      "category": "battle",
      "source": "Sahih al-Bukhari; Quran 3:123; Ibn Ishaq"
    },
    {
      "year": 625,
      "month": 3,
      "age": 54,
      "precision": "month",
      "location": "Mount Uhud (north of Medina)",
      "lat": 24.5065,
      "lng": 39.6119,
      "event": "The Battle of Uhud. The Muslim force suffered a setback when archers abandoned their positions. The Prophet was injured when struck by stones. Hamza ibn Abd al-Muttalib was killed.",
      "category": "battle",
      "source": "Sahih al-Bukhari; Quran 3:121-128; Ibn Ishaq"
    },
    {
      "year": 627,
      "month": 3,
      "age": 56,
      "precision": "month",
      "location": "Medina (Trench)",
      "lat": 24.4836,
      "lng": 39.6097,
      "event": "The Battle of the Trench (Khandaq). On the advice of Salman al-Farisi, a large trench was dug around Medina's exposed northern side. A coalition of 10,000 besieged the city for nearly a month but failed to breach the defences.",
      "category": "battle",
      "source": "Ibn Ishaq; Quran 33:9-27"
    },
    {
      "year": 628,
      "month": 3,
      "age": 57,
      "precision": "month",
      "location": "Hudaybiyyah (west of Mecca)",
      "lat": 21.4417,
      "lng": 39.6083,
      "event": "The Treaty of Hudaybiyyah. A ten-year truce was signed with the Quraysh. Though initially seen as unfavourable, the Quran called it a 'clear victory' (48:1). It allowed peaceful propagation of Islam across Arabia.",
      "category": "treaty",
      "source": "Sahih al-Bukhari; Quran 48:1; Ibn Ishaq"
    },
    {
      "year": 628,
      "month": 5,
      "age": 57,
      "precision": "month",
      "location": "Khaybar",
      "lat": 25.6989,
      "lng": 39.2928,
      "event": "The Conquest of Khaybar. The fortified oasis stronghold north of Medina was taken after a prolonged siege. Ali ibn Abi Talib led the final assault.",
      "category": "conquest",
      "source": "Sahih al-Bukhari; Ibn Ishaq"
    },
    {
      "year": 629,
      "month": 3,
      "age": 58,
      "precision": "month",
      "location": "Mecca (Ka'bah)",
      "lat": 21.4225,
      "lng": 39.8262,
      "event": "The Lesser Pilgrimage (Umrat al-Qada). Under the terms of Hudaybiyyah, the Muslims entered Mecca peacefully for three days to perform Umrah — their first return since the Hijra.",
      "category": "pilgrimage",
      "source": "Sahih al-Bukhari; Ibn Ishaq"
    },
    {
      "year": 629,
      "month": 9,
      "age": 58,
      "precision": "month",
      "location": "Mu'tah (southern Jordan)",
      "lat": 31.0533,
      "lng": 35.6922,
      "event": "The Battle of Mu'tah. An expedition of 3,000 Muslims faced a large Byzantine-allied force. Zayd ibn Harithah, Ja'far ibn Abi Talib, and Abdullah ibn Rawahah were killed. Khalid ibn al-Walid took command and withdrew the army safely.",
      "category": "battle",
      "source": "Sahih al-Bukhari; Ibn Ishaq"
    },
    {
      "year": 630,
      "month": 1,
      "age": 59,
      "precision": "month",
      "location": "Mecca",
      "lat": 21.4225,
      "lng": 39.8262,
      "event": "The Conquest of Mecca (Fath Makkah). An army of 10,000 entered the city with almost no resistance. The Prophet granted a general amnesty and cleansed the Ka'bah of its 360 idols, declaring 'Truth has come and falsehood has vanished.'",
      "category": "conquest",
      "source": "Sahih al-Bukhari; Sahih Muslim; Quran 17:81"
    },
    {
      "year": 630,
      "month": 1,
      "age": 59,
      "precision": "month",
      "location": "Hunayn Valley (east of Mecca)",
      "lat": 21.4500,
      "lng": 40.1000,
      "event": "The Battle of Hunayn. Immediately after the conquest, the Hawazin and Thaqif tribes attacked. The Muslims were initially ambushed in a narrow valley but rallied and won decisively.",
      "category": "battle",
      "source": "Quran 9:25-26; Sahih al-Bukhari"
    },
    {
      "year": 630,
      "month": 2,
      "age": 59,
      "precision": "month",
      "location": "Ta'if",
      "lat": 21.2703,
      "lng": 40.4158,
      "event": "The Siege of Ta'if. After Hunayn, the Muslim army besieged the fortified city of Ta'if for about twenty days. The siege was lifted without a decisive outcome; the Thaqif later voluntarily accepted Islam.",
      "category": "siege",
      "source": "Ibn Ishaq; Ibn Sa'd"
    },
    {
      "year": 630,
      "month": 10,
      "age": 60,
      "precision": "month",
      "location": "Tabuk (northern Arabia)",
      "lat": 28.3838,
      "lng": 36.5550,
      "event": "The Expedition to Tabuk. The largest military expedition, with 30,000 men marching north toward the Byzantine frontier. No battle occurred, but several northern tribes submitted. It demonstrated Muslim reach to the edge of the Byzantine Empire.",
      "category": "expedition",
      "source": "Quran 9:38-42; Ibn Ishaq"
    },
    {
      "year": 632,
      "month": 3,
      "age": 62,
      "precision": "month",
      "location": "Mount Arafat (near Mecca)",
      "lat": 21.3547,
      "lng": 39.9842,
      "event": "The Farewell Pilgrimage (Hajjat al-Wada'). Delivered the Farewell Sermon at Arafat before approximately 100,000 pilgrims, declaring the equality of all people, the sanctity of life and property, and the completion of the religion.",
      "category": "sermon",
      "source": "Sahih Muslim; Sahih al-Bukhari"
    },
    {
      "year": 632,
      "month": 6,
      "day": 8,
      "age": 62,
      "precision": "day",
      "location": "Medina (house of Aisha)",
      "lat": 24.4672,
      "lng": 39.6115,
      "event": "Died in the arms of Aisha in her chamber adjoining the Prophet's Mosque. His last words included counsel to uphold prayer and treat dependants well. He was buried where he passed away.",
      "category": "death",
      "source": "Sahih al-Bukhari; Sahih Muslim; Ibn Ishaq"
    }
  ]
}